dbs/__init__.py
dbs/browser/download.py
dbs/browser/login.py
dbs/gmail/__init__.py
dbs/gmail/credentials.py
dbs/gmail/gmail.py
dbs/gmail/quickstart.py
dbs/log.py
dbs/main.py
dbs/settings.py
dbs_statement_downloader-0.2.1.dist-info/LICENSE
dbs_statement_downloader-0.2.1.dist-info/METADATA
dbs_statement_downloader-0.2.1.dist-info/WHEEL
dbs_statement_downloader-0.2.1.dist-info/RECORD
