Metadata-Version: 2.1
Name: dbs-statement-downloader
Version: 0.2.1
Summary: Python library that downloads e-statements from DBS
Home-page: https://github.com/benjamin-awd/dbs-statement-downloader
License: MIT
Author: Benjamin Dornel
Author-email: benjamindornel@gmail.com
Requires-Python: >=3.11,<3.12
Classifier: Development Status :: 3 - Alpha
Classifier: License :: OSI Approved :: MIT License
Classifier: Programming Language :: Python :: 3
Classifier: Programming Language :: Python :: 3.11
Requires-Dist: google-api-python-client (>=2.111.0,<3.0.0)
Requires-Dist: google-auth (>=2.26.0,<3.0.0)
Requires-Dist: google-auth-oauthlib (>=1.2.0,<2.0.0)
Requires-Dist: google-cloud-secret-manager (>=2.17.0,<3.0.0)
Requires-Dist: google-cloud-storage (>=2.14.0,<3.0.0)
Requires-Dist: pydantic (>=2.5.3,<3.0.0)
Requires-Dist: pydantic-settings (>=2.1.0,<3.0.0)
Requires-Dist: python-dateutil (>=2.8.2,<3.0.0)
Requires-Dist: selenium (>=4.16.0,<5.0.0)
Project-URL: Repository, https://github.com/benjamin-awd/dbs-statement-downloader
